LICENSE
MANIFEST.in
README.rst
__init__.py
setup.cfg
setup.py
marionette_wrapper.egg-info/PKG-INFO
marionette_wrapper.egg-info/SOURCES.txt
marionette_wrapper.egg-info/dependency_links.txt
marionette_wrapper.egg-info/not-zip-safe
marionette_wrapper.egg-info/pbr.json
marionette_wrapper.egg-info/requires.txt
marionette_wrapper.egg-info/top_level.txt
marionettewrapper/__init__.py
marionettewrapper/base.py
marionettewrapper/helpers/__init__.py
marionettewrapper/helpers/utils.py
marionettewrapper/pages/__init__.py
marionettewrapper/pages/mozilla.py
marionettewrapper/pages/search_results.py
marionettewrapper/pages/yahoo.py
marionettewrapper/tests/__init__.py
marionettewrapper/tests/conftest.py
marionettewrapper/tests/test_marionette_wrapper_commands.py