Metadata-Version: 1.1
Name: marionette-wrapper
Version: 0.0.9.5
Summary: A wrapper for Marionette that increases test legibility
Home-page: https://github.com/mozilla-services/marionette-wrapper
Author: Mozilla Cloud Services QA Team
Author-email: cloud-services-qa@mozilla.com
License: MPL 2.0
Keywords: mozilla services
Platform: UNKNOWN
Classifier: Environment :: Console
Classifier: Intended Audience :: Developers
Classifier: License :: OSI Approved :: Mozilla Public License 2.0 (MPL 2.0)
Classifier: Natural Language :: English
Classifier: Operating System :: OS Independent
Classifier: Programming Language :: Python
Classifier: Topic :: Software Development :: Libraries :: Python Modules
